{
    "all_parents_bone": "root ground",
    "center_bone": "root hips",
    "groove_bone": "",
    "hip_bone": "",
    "upper_body_bone": "",
    "upper_body2_bone": "spine upper",
    "neck_bone": "head neck lower",
    "head_bone": "head neck upper",
    "left_shoulder_bone": "arm left shoulder 1",
    "right_shoulder_bone": "arm right shoulder 1",
    "left_upper_arm_bone": "arm left shoulder 2",
    "right_upper_arm_bone": "arm right shoulder 2",
    "left_lower_arm_bone": "arm left elbow",
    "right_lower_arm_bone": "arm right elbow",
    "left_hand_bone": "arm left wrist",
    "right_hand_bone": "arm right wrist",
    "lower_body_bone": "spine lower",
    "left_thigh_bone": "leg left thigh",
    "right_thigh_bone": "leg right thigh",
    "left_calf_bone": "leg left knee",
    "right_calf_bone": "leg right knee",
    "left_foot_bone": "leg left ankle",
    "right_foot_bone": "leg right ankle",
    "left_toe_bone": "",
    "right_toe_bone": "",
    "control_center_bone": "",
    "left_eye_bone": "head eyeball left",
    "right_eye_bone": "head eyeball right",
    "left_thumb_0": "arm left finger 1a",
    "left_thumb_1": "arm left finger 1b",
    "left_thumb_2": "arm left finger 1c",
    "right_thumb_0": "arm right finger 1a",
    "right_thumb_1": "arm right finger 1b",
    "right_thumb_2": "arm right finger 1c",
    "left_index_1": "arm left finger 2a",
    "left_index_2": "arm left finger 2b",
    "left_index_3": "arm left finger 2c",
    "right_index_1": "arm right finger 2a",
    "right_index_2": "arm right finger 2b",
    "right_index_3": "arm right finger 2c",
    "left_middle_1": "arm left finger 3a",
    "left_middle_2": "arm left finger 3b",
    "left_middle_3": "arm left finger 3c",
    "right_middle_1": "arm right finger 3a",
    "right_middle_2": "arm right finger 3b",
    "right_middle_3": "arm right finger 3c",
    "left_ring_1": "arm left finger 4a",
    "left_ring_2": "arm left finger 4b",
    "left_ring_3": "arm left finger 4c",
    "right_ring_1": "arm right finger 4a",
    "right_ring_2": "arm right finger 4b",
    "right_ring_3": "arm right finger 4c",
    "left_pinky_1": "arm left finger 5a",
    "left_pinky_2": "arm left finger 5b",
    "left_pinky_3": "arm left finger 5c",
    "right_pinky_1": "arm right finger 5a",
    "right_pinky_2": "arm right finger 5b",
    "right_pinky_3": "arm right finger 5c"
}